email2md/__init__.py
email2md/__main__.py
email2md-0.1.3.dist-info/METADATA
email2md-0.1.3.dist-info/WHEEL
email2md-0.1.3.dist-info/entry_points.txt
email2md-0.1.3.dist-info/licenses/LICENSE
email2md-0.1.3.dist-info/RECORD
