Metadata-Version: 2.4
Name: email2md
Version: 0.1.3
Summary: Pure Python EML and MSG converter
Author-email: Li Yang <hewliyang@u.nus.edu>
License-File: LICENSE
Requires-Python: >=3.10
Requires-Dist: extract-msg>=0.55.0
Requires-Dist: markdownify>=0.13.1
